clai/__init__.py
clai/__main__.py
clai-1.51.0.dist-info/METADATA
clai-1.51.0.dist-info/WHEEL
clai-1.51.0.dist-info/entry_points.txt
clai-1.51.0.dist-info/licenses/LICENSE
clai-1.51.0.dist-info/RECORD
